slidetemplater/api.py
slidetemplater-0.0.6.dist-info/LICENSE
slidetemplater-0.0.6.dist-info/METADATA
slidetemplater-0.0.6.dist-info/WHEEL
slidetemplater-0.0.6.dist-info/top_level.txt
slidetemplater-0.0.6.dist-info/RECORD
