Metadata-Version: 2.1
Name: slidetemplater
Version: 0.0.6
Summary: A client API for slidetemplater.com
Home-page: https://github.com/evolvedlight/slideplater-python
Author: Stephen Brown
Author-email: steve@slidetemplater.com
License: UNKNOWN
Platform: UNKNOWN
Classifier: Programming Language :: Python :: 3
Classifier: License :: OSI Approved :: MIT License
Classifier: Operating System :: OS Independent
Requires-Python: >=3.6
Requires-Dist: requests
